ampoule_ssg/__init__.py
ampoule_ssg/_utils.py
ampoule_ssg/extra_jinja.py
ampoule_ssg/markdown.py
ampoule_ssg-0.1.0.dist-info/LICENCE.md
ampoule_ssg-0.1.0.dist-info/METADATA
ampoule_ssg-0.1.0.dist-info/WHEEL
ampoule_ssg-0.1.0.dist-info/top_level.txt
ampoule_ssg-0.1.0.dist-info/RECORD
